distmetrics/__init__.py
distmetrics/asf_burst_search.py
distmetrics/asf_io.py
distmetrics/cusum.py
distmetrics/despeckle.py
distmetrics/logratio.py
distmetrics/mahalanobis.py
distmetrics/model_load.py
distmetrics/nd_tools.py
distmetrics/rio_tools.py
distmetrics/tf_inference.py
distmetrics/tf_metric.py
distmetrics/tf_model.py
distmetrics/model_data/transformer_anniversary_trained/config.json
distmetrics/model_data/transformer_anniversary_trained/weights.pth
distmetrics/model_data/transformer_anniversary_trained_10/config.json
distmetrics/model_data/transformer_anniversary_trained_10/weights.pth
distmetrics/model_data/transformer_anniversary_trained_optimized/config.json
distmetrics/model_data/transformer_anniversary_trained_optimized/weights.pth
distmetrics/model_data/transformer_anniversary_trained_optimized_fine/config.json
distmetrics/model_data/transformer_anniversary_trained_optimized_fine/weights.pth
distmetrics/model_data/transformer_optimized/config.json
distmetrics/model_data/transformer_optimized/weights.pth
distmetrics/model_data/transformer_optimized_fine/config.json
distmetrics/model_data/transformer_optimized_fine/weights.pth
distmetrics/model_data/transformer_original/config.json
distmetrics/model_data/transformer_original/weights.pth
distmetrics/model_data/transformer_v0_32/config.json
distmetrics/model_data/transformer_v0_32/weights.pth
distmetrics/model_data/transformer_v1_32/config.json
distmetrics/model_data/transformer_v1_32/weights.pth
distmetrics-1.0.6.dist-info/licenses/LICENSE.txt
distmetrics-1.0.6.dist-info/METADATA
distmetrics-1.0.6.dist-info/WHEEL
distmetrics-1.0.6.dist-info/top_level.txt
distmetrics-1.0.6.dist-info/zip-safe
distmetrics-1.0.6.dist-info/RECORD
