Metadata-Version: 2.4
Name: distmetrics
Version: 1.0.6
Summary: Measure Disturbances in OPERA RTC-S1 Stacks
Author-email: "Jungkyo Jung, Charlie Marshak, Talib Oliver-Cabrera, Richard West and OPERA Team" <opera-pst-dev@jpl.nasa.gov>
License: Apache-2.0
Project-URL: Homepage, https://github.com/opera-adt/distmetrics
Project-URL: Bug Tracker, https://github.com/opera-adt/distmetrics/issues
Classifier: Intended Audience :: Science/Research
Classifier: Natural Language :: English
Classifier: Operating System :: OS Independent
Classifier: Natural Language :: English
Classifier: Programming Language :: Python :: 3
Classifier: Programming Language :: Python :: 3.12
Classifier: Programming Language :: Python :: 3.13
Requires-Python: >=3.12
License-File: LICENSE.txt
Requires-Dist: affine
Requires-Dist: asf_search
Requires-Dist: astropy
Requires-Dist: backoff
Requires-Dist: einops
Requires-Dist: geopandas
Requires-Dist: matplotlib
Requires-Dist: numpy
Requires-Dist: pandas
Requires-Dist: pydantic
Requires-Dist: torch
Requires-Dist: rasterio
Requires-Dist: scikit-image
Requires-Dist: scipy
Requires-Dist: shapely
Requires-Dist: tqdm
Provides-Extra: develop
Requires-Dist: pytest; extra == "develop"
Requires-Dist: pytest-cov; extra == "develop"
Requires-Dist: flake8; extra == "develop"
Requires-Dist: flake8-import-order; extra == "develop"
Requires-Dist: flake8-blind-except; extra == "develop"
Requires-Dist: flake8-builtins; extra == "develop"
Requires-Dist: jupyterlab; extra == "develop"
Dynamic: license-file
